ssdtm/__init__.py
ssdtm/__main__.py
ssdtm/cli.py
ssdtm-0.1.3.dist-info/METADATA
ssdtm-0.1.3.dist-info/WHEEL
ssdtm-0.1.3.dist-info/top_level.txt
ssdtm-0.1.3.dist-info/RECORD
