Metadata-Version: 2.1
Name: ssdtm
Version: 0.1.3
Summary: A package that can generate low-fidelity synthetic CDISC SDTM data based on intelligent sequence generators
Author: Akshay Chougule
Author-email: akshay6023@gmail.com
License: MIT
Project-URL: source, https://github.com/AksChougule/gen-sdtm
Classifier: Intended Audience :: Science/Research
Classifier: Development Status :: 2 - Pre-Alpha
Classifier: Operating System :: OS Independent
Classifier: Programming Language :: Python :: 3.7
Classifier: Programming Language :: Python :: 3.8
Classifier: Programming Language :: Python :: 3.9
Classifier: Programming Language :: Python :: 3.10
Classifier: Programming Language :: Python :: 3.11
Requires-Python: >=3.7
Requires-Dist: pandas
Requires-Dist: numpy
Requires-Dist: datetime
